plover_q_and_a/__init__.py
plover_q_and_a/extension.py
plover_q_and_a/config/__init__.py
plover_q_and_a/config/extractor.py
plover_q_and_a/config/loader.py
plover_q_and_a/config/transformer/__init__.py
plover_q_and_a/config/transformer/answer.py
plover_q_and_a/config/transformer/byline.py
plover_q_and_a/config/transformer/question.py
plover_q_and_a/config/transformer/sentence_ending.py
plover_q_and_a/config/transformer/set_name.py
plover_q_and_a/config/transformer/speaker.py
plover_q_and_a/sign/__init__.py
plover_q_and_a/sign/answer.py
plover_q_and_a/sign/byline.py
plover_q_and_a/sign/follow_on.py
plover_q_and_a/sign/question.py
plover_q_and_a/sign/speaker.py
plover_q_and_a/sign/text.py
plover_q_and_a/speaker/__init__.py
plover_q_and_a/speaker/formatting.py
plover_q_and_a/speaker/set_name.py
plover_q_and_a-0.4.4.dist-info/LICENSE.txt
plover_q_and_a-0.4.4.dist-info/METADATA
plover_q_and_a-0.4.4.dist-info/WHEEL
plover_q_and_a-0.4.4.dist-info/entry_points.txt
plover_q_and_a-0.4.4.dist-info/top_level.txt
plover_q_and_a-0.4.4.dist-info/zip-safe
plover_q_and_a-0.4.4.dist-info/RECORD
